Workbook

Sheet Dashboard
A1: 🕯️ VELAS — Dashboard de Gestão
A2: Atualizado em 16/05/2026
A4: 📈 Vendas Totais | C4: 📅 Este Mês | E4: 💰 Lucro Estimado | G4: ⏳ Pendentes | I4: 📦 Valor Inventário | K4: 🕯️ Stock Velas
A5: =SUMIFS(Vendas!G:G,Vendas!I:I,"<>Cancelada") -> 307.4 | C5: =SUMPRODUCT((MONTH(Vendas!B3:B1000)=MONTH(TODAY()))*(YEAR(Vendas!B3:B1000)=YEAR(TODAY()))*(Vendas!I3:I1000<>"Cancelada")*Vendas!G3:G1000) -> 0 | E5: =SUMIFS(Vendas!G:G,Vendas!I:I,"<>Cancelada")-SUM(Gastos!E:E) -> -885.6 | G5: =COUNTIF(Vendas!I:I,"Pendente") -> 1 | I5: =SUMPRODUCT(Inventário!E3:E1000,Inventário!F3:F1000) -> 405 | K5: =SUM(Stock!E:E) -> 122
A10: 📅 Vendas Mensais 2025 | F10: 💸 Despesas por Categoria
A11: Mês | B11: Vendas (€) | C11: Despesas (€) | D11: Lucro (€) | F11: Categoria | G11: Total (€) | H11: % do Total
A12: Jan 2025 | B12: =SUMPRODUCT((MONTH(Vendas!$B$3:$B$1000)=1)*(YEAR(Vendas!$B$3:$B$1000)=2025)*(Vendas!$I$3:$I$1000<>"Cancelada")*Vendas!$G$3:$G$1000) -> 29.7 | C12: =SUMPRODUCT((MONTH(Gastos!$B$3:$B$1000)=1)*(YEAR(Gastos!$B$3:$B$1000)=2025)*Gastos!$E$3:$E$1000) -> 146 | D12: =B12-C12 -> -116.3 | F12: Matérias-Primas | G12: =SUMIF(Gastos!$D$3:$D$1000,F12,Gastos!$E$3:$E$1000) -> 231 | H12: =IFERROR(G12/SUM(Gastos!$E$3:$E$1000),0) -> 0.19362951
A13: Fev 2025 | B13: =SUMPRODUCT((MONTH(Vendas!$B$3:$B$1000)=2)*(YEAR(Vendas!$B$3:$B$1000)=2025)*(Vendas!$I$3:$I$1000<>"Cancelada")*Vendas!$G$3:$G$1000) -> 19.8 | C13: =SUMPRODUCT((MONTH(Gastos!$B$3:$B$1000)=2)*(YEAR(Gastos!$B$3:$B$1000)=2025)*Gastos!$E$3:$E$1000) -> 320 | D13: =B13-C13 -> -300.2 | F13: Embalagem | G13: =SUMIF(Gastos!$D$3:$D$1000,F13,Gastos!$E$3:$E$1000) -> 240 | H13: =IFERROR(G13/SUM(Gastos!$E$3:$E$1000),0) -> 0.20117351
A14: Mar 2025 | B14: =SUMPRODUCT((MONTH(Vendas!$B$3:$B$1000)=3)*(YEAR(Vendas!$B$3:$B$1000)=2025)*(Vendas!$I$3:$I$1000<>"Cancelada")*Vendas!$G$3:$G$1000) -> 24.9 | C14: =SUMPRODUCT((MONTH(Gastos!$B$3:$B$1000)=3)*(YEAR(Gastos!$B$3:$B$1000)=2025)*Gastos!$E$3:$E$1000) -> 45.5 | D14: =B14-C14 -> -20.6 | F14: Marketing | G14: =SUMIF(Gastos!$D$3:$D$1000,F14,Gastos!$E$3:$E$1000) -> 80 | H14: =IFERROR(G14/SUM(Gastos!$E$3:$E$1000),0) -> 0.067057837
A15: Abr 2025 | B15: =SUMPRODUCT((MONTH(Vendas!$B$3:$B$1000)=4)*(YEAR(Vendas!$B$3:$B$1000)=2025)*(Vendas!$I$3:$I$1000<>"Cancelada")*Vendas!$G$3:$G$1000) -> 29.8 | C15: =SUMPRODUCT((MONTH(Gastos!$B$3:$B$1000)=4)*(YEAR(Gastos!$B$3:$B$1000)=2025)*Gastos!$E$3:$E$1000) -> 85 | D15: =B15-C15 -> -55.2 | F15: Transporte | G15: =SUMIF(Gastos!$D$3:$D$1000,F15,Gastos!$E$3:$E$1000) -> 45.5 | H15: =IFERROR(G15/SUM(Gastos!$E$3:$E$1000),0) -> 0.038139145
A16: Mai 2025 | B16: =SUMPRODUCT((MONTH(Vendas!$B$3:$B$1000)=5)*(YEAR(Vendas!$B$3:$B$1000)=2025)*(Vendas!$I$3:$I$1000<>"Cancelada")*Vendas!$G$3:$G$1000) -> 49.5 | C16: =SUMPRODUCT((MONTH(Gastos!$B$3:$B$1000)=5)*(YEAR(Gastos!$B$3:$B$1000)=2025)*Gastos!$E$3:$E$1000) -> 0 | D16: =B16-C16 -> 49.5 | F16: Equipamento | G16: =SUMIF(Gastos!$D$3:$D$1000,F16,Gastos!$E$3:$E$1000) -> 0 | H16: =IFERROR(G16/SUM(Gastos!$E$3:$E$1000),0) -> 0
A17: Jun 2025 | B17: =SUMPRODUCT((MONTH(Vendas!$B$3:$B$1000)=6)*(YEAR(Vendas!$B$3:$B$1000)=2025)*(Vendas!$I$3:$I$1000<>"Cancelada")*Vendas!$G$3:$G$1000) -> 0 | C17: =SUMPRODUCT((MONTH(Gastos!$B$3:$B$1000)=6)*(YEAR(Gastos!$B$3:$B$1000)=2025)*Gastos!$E$3:$E$1000) -> 0 | D17: =B17-C17 -> 0 | F17: Outro | G17: =SUMIF(Gastos!$D$3:$D$1000,F17,Gastos!$E$3:$E$1000) -> 0 | H17: =IFERROR(G17/SUM(Gastos!$E$3:$E$1000),0) -> 0
A18: Jul 2025 | B18: =SUMPRODUCT((MONTH(Vendas!$B$3:$B$1000)=7)*(YEAR(Vendas!$B$3:$B$1000)=2025)*(Vendas!$I$3:$I$1000<>"Cancelada")*Vendas!$G$3:$G$1000) -> 0 | C18: =SUMPRODUCT((MONTH(Gastos!$B$3:$B$1000)=7)*(YEAR(Gastos!$B$3:$B$1000)=2025)*Gastos!$E$3:$E$1000) -> 0 | D18: =B18-C18 -> 0 | F18: TOTAL | G18: =SUM(G12:G17) -> 596.5 | H18: 100%
A19: Ago 2025 | B19: =SUMPRODUCT((MONTH(Vendas!$B$3:$B$1000)=8)*(YEAR(Vendas!$B$3:$B$1000)=2025)*(Vendas!$I$3:$I$1000<>"Cancelada")*Vendas!$G$3:$G$1000) -> 0 | C19: =SUMPRODUCT((MONTH(Gastos!$B$3:$B$1000)=8)*(YEAR(Gastos!$B$3:$B$1000)=2025)*Gastos!$E$3:$E$1000) -> 0 | D19: =B19-C19 -> 0
A20: Set 2025 | B20: =SUMPRODUCT((MONTH(Vendas!$B$3:$B$1000)=9)*(YEAR(Vendas!$B$3:$B$1000)=2025)*(Vendas!$I$3:$I$1000<>"Cancelada")*Vendas!$G$3:$G$1000) -> 0 | C20: =SUMPRODUCT((MONTH(Gastos!$B$3:$B$1000)=9)*(YEAR(Gastos!$B$3:$B$1000)=2025)*Gastos!$E$3:$E$1000) -> 0 | D20: =B20-C20 -> 0
A21: Out 2025 | B21: =SUMPRODUCT((MONTH(Vendas!$B$3:$B$1000)=10)*(YEAR(Vendas!$B$3:$B$1000)=2025)*(Vendas!$I$3:$I$1000<>"Cancelada")*Vendas!$G$3:$G$1000) -> 0 | C21: =SUMPRODUCT((MONTH(Gastos!$B$3:$B$1000)=10)*(YEAR(Gastos!$B$3:$B$1000)=2025)*Gastos!$E$3:$E$1000) -> 0 | D21: =B21-C21 -> 0
A22: Nov 2025 | B22: =SUMPRODUCT((MONTH(Vendas!$B$3:$B$1000)=11)*(YEAR(Vendas!$B$3:$B$1000)=2025)*(Vendas!$I$3:$I$1000<>"Cancelada")*Vendas!$G$3:$G$1000) -> 0 | C22: =SUMPRODUCT((MONTH(Gastos!$B$3:$B$1000)=11)*(YEAR(Gastos!$B$3:$B$1000)=2025)*Gastos!$E$3:$E$1000) -> 0 | D22: =B22-C22 -> 0
A23: Dez 2025 | B23: =SUMPRODUCT((MONTH(Vendas!$B$3:$B$1000)=12)*(YEAR(Vendas!$B$3:$B$1000)=2025)*(Vendas!$I$3:$I$1000<>"Cancelada")*Vendas!$G$3:$G$1000) -> 0 | C23: =SUMPRODUCT((MONTH(Gastos!$B$3:$B$1000)=12)*(YEAR(Gastos!$B$3:$B$1000)=2025)*Gastos!$E$3:$E$1000) -> 0 | D23: =B23-C23 -> 0
A24: TOTAL | B24: =SUM(B12:B23) -> 153.7 | C24: =SUM(C12:C23) -> 596.5 | D24: =SUM(D12:D23) -> -442.8

Sheet Inventário
A1: 📦 Inventário de Matérias-Primas
A2: ID | B2: Nome | C2: Tipo | D2: Unidade | E2: Quantidade | F2: Preço/Unid. | G2: Valor Total | H2: Stock Mín. | I2: Fornecedor | J2: Estado | K2: Notas
A3: INV001 | B3: Cera de Soja | C3: Cera | D3: kg | E3: 10 | F3: 4.5 | G3: =E3*F3 -> 45 | H3: 5 | I3: AromaShop | J3: =IF(H3>0,IF(E3<=H3,"⚠️ Baixo","✅ OK"),"—") -> ✅ OK | K3: Soja natural 464
A4: INV002 | B4: Essência Lavanda | C4: Essência | D4: kg | E4: 2 | F4: 28 | G4: =E4*F4 -> 56 | H4: 0.5 | I4: AromaShop | J4: =IF(H4>0,IF(E4<=H4,"⚠️ Baixo","✅ OK"),"—") -> ✅ OK
A5: INV003 | B5: Copos de Vidro 20cl | C5: Recipiente | D5: unidade(s) | E5: 200 | F5: 1.2 | G5: =E5*F5 -> 240 | H5: 50 | I5: VidroCasa | J5: =IF(H5>0,IF(E5<=H5,"⚠️ Baixo","✅ OK"),"—") -> ✅ OK
A6: INV004 | B6: Pavios Algodão CD14 | C6: Pavio | D6: unidade(s) | E6: 500 | F6: 0.1 | G6: =E6*F6 -> 50 | H6: 100 | I6: CandleShop | J6: =IF(H6>0,IF(E6<=H6,"⚠️ Baixo","✅ OK"),"—") -> ✅ OK | K6: CD14 para copos 7-8cm
A7: INV005 | B7: Cimento Branco | C7: Cimento | D7: kg | E7: 5 | F7: 2.8 | G7: =E7*F7 -> 14 | H7: 2 | I7: BricoMarkt | J7: =IF(H7>0,IF(E7<=H7,"⚠️ Baixo","✅ OK"),"—") -> ✅ OK | K7: Fino, para moldes
A8: TOTAL | G8: =SUM(G3:G7) -> 405

Sheet Calculadora
A1: 🧮 Calculadora de Fabricação de Velas
A2: ⚙️ Parâmetros de Produção (alterar células a azul)
A3: Nº de Velas | B3: 100
A4: Peso por Vela (g) | B4: 200 | C4: g
A5: % de Essência | B5: 0.08 | C5: %
A6: Preço da Cera (€/kg) | B6: 4.5 | C6: €/kg
A7: Preço da Essência (€/kg) | B7: 25 | C7: €/kg
A8: Custo Recipiente (€/un) | B8: 1.2 | C8: €/un
A9: Custo Pavio (€/un) | B9: 0.1 | C9: €/un
A10: Custo Etiqueta (€/un) | B10: 0.08 | C10: €/un
A11: Outros Custos Fixos (€) | B11: 0 | C11: €
A12: Margem de Lucro | B12: 0.4 | C12: %
A14: 📋 Resultados Calculados
A15: Peso Total do Lote (g) | B15: =B3*B4 -> 20000 | C15: g
A16: Essência Necessária (g) | B16: =B15*B5 -> 1600 | C16: g
A17: Cera Necessária (kg) | B17: =(B15-B16)/1000 -> 18.4 | C17: kg
A18: Essência Necessária (kg) | B18: =B16/1000 -> 1.6 | C18: kg
A19: — Custo Cera (€) | B19: =B17*B6 -> 82.8 | C19: €
A20: — Custo Essência (€) | B20: =B18*B7 -> 40 | C20: €
A21: — Custo Recipientes (€) | B21: =B3*B8 -> 120 | C21: €
A22: — Custo Pavios (€) | B22: =B3*B9 -> 10 | C22: €
A23: — Custo Etiquetas (€) | B23: =B3*B10 -> 8 | C23: €
A24: — Outros Custos Fixos (€) | B24: =B11 -> 0 | C24: €
A25: 💶 CUSTO TOTAL DO LOTE (€) | B25: =SUM(B19:B24) -> 260.8
A26: 💰 CUSTO POR VELA (€) | B26: =IF(B3>0,B25/B3,0) -> 2.608
A27: 🏷️ PVP SUGERIDO (€) | B27: =B26*(1+B12) -> 3.6512
A29: 📊 Distribuição de Custos do Lote
A30: Componente | B30: Custo (€)
A31: Cera | B31: =B19 -> 82.8
A32: Essência | B32: =B20 -> 40
A33: Recipiente | B33: =B21 -> 120
A34: Pavio | B34: =B22 -> 10
A35: Etiqueta | B35: =B23 -> 8
A36: Outros | B36: =B24 -> 0
A40: 📁 Lotes Guardados
A41: Nome do Lote | B41: Data | C41: Nº Velas | D41: Cera (kg) | E41: Essência (g) | F41: Custo Total | G41: Custo/Vela | H41: PVP Sugerido

Sheet Receitas
A1: 🧪 Receitas de Velas — Fórmulas e Combinações
A2: ID | B2: Nome | C2: Tipo Cera | D2: Peso (g) | E2: % Essência | F2: Temp. (°C) | G2: Tipo Pavio | H2: Recipiente | I2: Cura (h) | J2: Fragrâncias | K2: Corante | L2: Avaliação ⭐ | M2: Notas | N2: Data
A3: REC001 | B3: Lavanda & Baunilha | C3: Soja | D3: 200 | E3: 0.08 | F3: 55 | G3: CD14 | H3: Copo Vidro 20cl | I3: 48 | J3: Lavanda 6% + Baunilha 2% | K3: Roxo — 2 gotas/100g | L3: ⭐⭐⭐⭐⭐ | M3: Burn test OK. Cheiro forte e duradouro. | N3: 2025-01-20
A4: REC002 | B4: Cimento Nórdico | C4: Soja + Coco 80/20 | D4: 180 | E4: 0.07 | F4: 52 | G4: ECO4 | H4: Molde Cimento | I4: 72 | J4: Eucalipto 5% + Alecrim 2% | K4: Sem corante | L4: ⭐⭐⭐⭐ | M4: Tempo de cura mais longo. Acabamento rústico. | N4: 2025-02-10

Sheet Stock
A1: 🕯️ Stock de Velas Acabadas
A2: ID | B2: Nome | C2: Essência | D2: Tamanho | E2: Quantidade | F2: Preço Custo | G2: PVP | H2: Valor Stock | I2: Margem % | J2: Estado
A3: STK001 | B3: Vela Lavanda 200g | C3: Lavanda | D3: 200g | E3: 45 | F3: 2.85 | G3: 9.9 | H3: =E3*G3 -> 445.5 | I3: =IF(F3>0,(G3-F3)/F3,0) -> 2.4736842 | J3: =IF(E3=0,"❌ Esgotado",IF(E3<5,"⚠️ Baixo","✅ OK")) -> ✅ OK
A4: STK002 | B4: Vela Baunilha 200g | C4: Baunilha | D4: 200g | E4: 12 | F4: 2.85 | G4: 9.9 | H4: =E4*G4 -> 118.8 | I4: =IF(F4>0,(G4-F4)/F4,0) -> 2.4736842 | J4: =IF(E4=0,"❌ Esgotado",IF(E4<5,"⚠️ Baixo","✅ OK")) -> ✅ OK
A5: STK003 | B5: Vela Cimento Nórdico | C5: Eucalipto+Alecrim | D5: 180g | E5: 4 | F5: 3.2 | G5: 14.9 | H5: =E5*G5 -> 59.6 | I5: =IF(F5>0,(G5-F5)/F5,0) -> 3.65625 | J5: =IF(E5=0,"❌ Esgotado",IF(E5<5,"⚠️ Baixo","✅ OK")) -> ⚠️ Baixo
A6: TOTAL | E6: =SUM(E3:E5) -> 61 | H6: =SUM(H3:H5) -> 623.9 | I6: =IFERROR(AVERAGE(I3:I5),0) -> 2.8678728

Sheet Vendas
A1: 🛒 Vendas & Encomendas
A2: ID | B2: Data | C2: Cliente | D2: Produto | E2: Quantidade | F2: Preço/Un. | G2: Total | H2: Pagamento | I2: Estado | J2: Notas
A3: VND001 | B3: 2025-01-15 | C3: Maria Santos | D3: Vela Lavanda 200g | E3: 3 | F3: 9.9 | G3: =E3*F3 -> 29.7 | H3: MB Way | I3: Entregue
A4: VND002 | B4: 2025-02-03 | C4: João Ferreira | D4: Vela Baunilha 200g | E4: 2 | F4: 9.9 | G4: =E4*F4 -> 19.8 | H4: Transferência | I4: Entregue
A5: VND003 | B5: 2025-03-10 | C5: Ana Costa | D5: Pack 3 Velas Sortidas | E5: 1 | F5: 24.9 | G5: =E5*F5 -> 24.9 | H5: MB Way | I5: Enviada | J5: Envio CTT
A6: VND004 | B6: 2025-04-22 | C6: Carlos Lopes | D6: Vela Cimento Nórdico | E6: 2 | F6: 14.9 | G6: =E6*F6 -> 29.8 | I6: Pendente | J6: Aguarda confirmação
A7: VND005 | B7: 2025-05-01 | C7: Rita Oliveira | D7: Vela Lavanda 200g | E7: 5 | F7: 9.9 | G7: =E7*F7 -> 49.5 | H7: Numerário | I7: A Processar
A8: TOTAL | G8: =SUM(G3:G7) -> 153.7

Sheet Gastos
A1: 💸 Gastos & Despesas
A2: ID | B2: Data | C2: Descrição | D2: Categoria | E2: Valor (€) | F2: Fornecedor | G2: Notas | I2: Categoria | J2: Total (€) | K2: % do Total
A3: GST001 | B3: 2025-01-10 | C3: Cera de Soja 20kg | D3: Matérias-Primas | E3: 90 | F3: AromaShop | I3: Matérias-Primas | J3: =SUMIF(D$3:D$1000,I3,E$3:E$1000) -> 231 | K3: =IFERROR(J3/J10,0) -> 0.38725901
A4: GST002 | B4: 2025-01-10 | C4: Essências variadas 2kg | D4: Matérias-Primas | E4: 56 | F4: AromaShop | I4: Embalagem | J4: =SUMIF(D$3:D$1000,I4,E$3:E$1000) -> 240 | K4: =IFERROR(J4/J10,0) -> 0.40234702
A5: GST003 | B5: 2025-02-05 | C5: Copos de Vidro x200 | D5: Embalagem | E5: 240 | F5: VidroCasa | I5: Marketing | J5: =SUMIF(D$3:D$1000,I5,E$3:E$1000) -> 80 | K5: =IFERROR(J5/J10,0) -> 0.13411567
A6: GST004 | B6: 2025-02-20 | C6: Fotografia de produtos | D6: Marketing | E6: 80 | F6: Studio Foto | G6: Sessão produto | I6: Transporte | J6: =SUMIF(D$3:D$1000,I6,E$3:E$1000) -> 45.5 | K6: =IFERROR(J6/J10,0) -> 0.07627829
A7: GST005 | B7: 2025-03-15 | C7: Envios CTT Março | D7: Transporte | E7: 45.5 | F7: CTT | I7: Equipamento | J7: =SUMIF(D$3:D$1000,I7,E$3:E$1000) -> 0 | K7: =IFERROR(J7/J10,0) -> 0
A8: GST006 | B8: 2025-04-01 | C8: Pavios x1000 | D8: Matérias-Primas | E8: 85 | F8: CandleShop | I8: Outro | J8: =SUMIF(D$3:D$1000,I8,E$3:E$1000) -> 0 | K8: =IFERROR(J8/J10,0) -> 0
A9: TOTAL | E9: =SUM(E3:E8) -> 596.5
I10: TOTAL | J10: =SUM(J3:J9) -> 596.5 | K10: 100%

Sheet Listas
A1: TiposInv | B1: Unidades | C1: EstadosOrdem | D1: Pagamentos | E1: Categorias
A2: Cera | B2: kg | C2: Pendente | D2: MB Way | E2: Matérias-Primas
A3: Essência | B3: g | C3: A Processar | D3: Multibanco | E3: Embalagem
A4: Pavio | B4: L | C4: Enviada | D4: Transferência | E4: Marketing
A5: Autocolante | B5: ml | C5: Entregue | D5: Numerário | E5: Transporte
A6: Recipiente | B6: unidade(s) | C6: Cancelada | D6: PayPal | E6: Equipamento
A7: Embalagem | B7: caixa(s) | E7: Outro
A8: Cimento | B8: rolo(s)
A9: Gesso | B9: saco(s)
A10: Areia
A11: Molde
A12: Corante
A13: Aditivo
A14: Outro
